[
    {
      "name": "Alija Miguel",
      "chesscoin": 0
    },
    {
      "name": "Almeida Enrique",
      "chesscoin": 4
    },
    {
      "name": "Aranibar Osvaldo",
      "chesscoin": 10
    },
    {
      "name": "Araujo Mateo",
      "chesscoin": 28
    },
    {
      "name": "Araya Manuel",
      "chesscoin": 15
    },
    {
      "name": "Ardiles Manuel",
      "chesscoin": 217
    },
    {
      "name": "Arias Leonardo",
      "chesscoin": 93
    },
    {
      "name": "Amadeo Pablo",
      "chesscoin": 13
    },
    {
      "name": "Banga Horacio",
      "chesscoin": 21
    },
    {
      "name": "Barbosa YAN",
      "chesscoin": 11
    },
    {
      "name": "Bascher Jorge",
      "chesscoin": 26
    },
    {
      "name": "Biancosino Rafael",
      "chesscoin": -4
    },
    {
      "name": "Bogado Luis",
      "chesscoin": 51
    },
    {
      "name": "Bova Carmelo",
      "chesscoin": 70
    },
    {
      "name": "Buscia Juan",
      "chesscoin": 45
    },
    {
      "name": "Bustamante Fabian",
      "chesscoin": 15
    },
    {
      "name": "Cabral Carlos",
      "chesscoin": 18
    },
    {
      "name": "Cabrera Matias Gaston",
      "chesscoin": 44
    },
    {
      "name": "Carrizo Franco",
      "chesscoin": 24
    },
    {
      "name": "Chiguay Tomas Agustin",
      "chesscoin": 22
    },
    {
      "name": "Churukian Gregorio",
      "chesscoin": 51
    },
    {
      "name": "Ciancio Luis Juan",
      "chesscoin": 47
    },
    {
      "name": "Cisneros Juan",
      "chesscoin": -13
    },
    {
      "name": "Colque Alvaro",
      "chesscoin": 29
    },
    {
      "name": "Conde Adrian",
      "chesscoin": 0
    },
    {
      "name": "Conti Claudio",
      "chesscoin": 7
    },
    {
      "name": "Coria Miguel",
      "chesscoin": 2
    },
    {
      "name": "Coro Richard",
      "chesscoin": 74
    },
    {
      "name": "Da Silva Juan Manuel",
      "chesscoin": 17
    },
    {
      "name": "De Rovere Fernando",
      "chesscoin": 38
    },
    {
      "name": "Delgado Raul",
      "chesscoin": 4
    },
    {
      "name": "Diaz Adolfo",
      "chesscoin": 27
    },
    {
      "name": "Doisenbant Eduardo",
      "chesscoin": 124
    },
    {
      "name": "Doti Juan",
      "chesscoin": 43
    },
    {
      "name": "Ducros Marcelo",
      "chesscoin": 246
    },
    {
      "name": "Duri Alan",
      "chesscoin": 8
    },
    {
      "name": "Edgar Roberto",
      "chesscoin": 354
    },
    {
      "name": "Fernandez Pablo",
      "chesscoin": 1
    },
    {
      "name": "Fernandez Mauricio",
      "chesscoin": 28
    },
    {
      "name": "Ferraro Carlos",
      "chesscoin": 144
    },
    {
      "name": "Frangione Francisco",
      "chesscoin": 92
    },
    {
      "name": "Gaglarco Ricardo",
      "chesscoin": 15
    },
    {
      "name": "Galo Martin",
      "chesscoin": 5
    },
    {
      "name": "Gerola Pablo",
      "chesscoin": 0
    },
    {
      "name": "Gomez Vera Maximiliano",
      "chesscoin": 155
    },
    {
      "name": "Gonzalez Federico",
      "chesscoin": 0
    },
    {
      "name": "Gonzalez Fernando",
      "chesscoin": 30
    },
    {
      "name": "Gonzalez Pablo",
      "chesscoin": 32
    },
    {
      "name": "Granillo Eloy Hernan",
      "chesscoin": 14
    },
    {
      "name": "Gutierrez Ezequiel",
      "chesscoin": 0
    },
    {
      "name": "Herrera Pablo",
      "chesscoin": 335
    },
    {
      "name": "Izurreta Carlos",
      "chesscoin": 48
    },
    {
      "name": "Jaime Pedro",
      "chesscoin": 23
    },
    {
      "name": "Jorge Cristian",
      "chesscoin": 22
    },
    {
      "name": "Krywoszyja Ivan Muriel",
      "chesscoin": 132
    },
    {
      "name": "Lisardo Julio",
      "chesscoin": 7
    },
    {
      "name": "Maciel Sebastian",
      "chesscoin": 95
    },
    {
      "name": "Marina Adrian",
      "chesscoin": 38
    },
    {
      "name": "Migliavacca Carlos",
      "chesscoin": 125
    },
    {
      "name": "Milla Leandro Javier",
      "chesscoin": 135
    },
    {
      "name": "Minvielle Nehuen Alexis",
      "chesscoin": 17
    },
    {
      "name": "Miserendino Alfredo",
      "chesscoin": 163
    },
    {
      "name": "Montedonico Jose",
      "chesscoin": 130
    },
    {
      "name": "Moreno Javier Gonzalo",
      "chesscoin": -30
    },
    {
      "name": "Nami Ruben",
      "chesscoin": 21
    },
    {
      "name": "Navarro Alberto",
      "chesscoin": 33
    },
    {
      "name": "Ostoich Mariano",
      "chesscoin": -100
    },
    {
      "name": "Ostos Juan",
      "chesscoin": 15
    },
    {
      "name": "Oyarzu Eduardo",
      "chesscoin": 50
    },
    {
      "name": "Perez Wertheim Rodolfo",
      "chesscoin": 163
    },
    {
      "name": "Pizarro Jeronimo",
      "chesscoin": 36
    },
    {
      "name": "Plana Jose",
      "chesscoin": 53
    },
    {
      "name": "Polo Pablo (Loana)",
      "chesscoin": 0
    },
    {
      "name": "Quiñones Hector",
      "chesscoin": 66
    },
    {
      "name": "Quiroga Luis Alberto",
      "chesscoin": 29
    },
    {
      "name": "Raffin Marcelo",
      "chesscoin": 53
    },
    {
      "name": "Rasgido Alejandro",
      "chesscoin": 92
    },
    {
      "name": "Rey Barassi Roberto",
      "chesscoin": -25
    },
    {
      "name": "Rivero Jorge",
      "chesscoin": 163
    },
    {
      "name": "Rodriguez Hernan",
      "chesscoin": 7
    },
    {
      "name": "Rodriguez Vargas Sergio",
      "chesscoin": 122
    },
    {
      "name": "Roguin Nestor",
      "chesscoin": 229
    },
    {
      "name": "Roman Vicente",
      "chesscoin": 0
    },
    {
      "name": "Romanach Hernan",
      "chesscoin": 34
    },
    {
      "name": "Ruffo Teo",
      "chesscoin": -31
    },
    {
      "name": "Ruiz Diaz Alfredo",
      "chesscoin": 112
    },
    {
      "name": "Saez Diego",
      "chesscoin": 56
    },
    {
      "name": "Salgado Jose",
      "chesscoin": 18
    },
    {
      "name": "Shab Lautaro",
      "chesscoin": 16
    },
    {
      "name": "Sanchez Gonzalo",
      "chesscoin": 17
    },
    {
      "name": "Sciascia Roberto",
      "chesscoin": 25
    },
    {
      "name": "Schafer, Marcelo",
      "chesscoin": 52
    },
    {
      "name": "Serratto Ricardo",
      "chesscoin": 198
    },
    {
      "name": "Sgro Maximiliano",
      "chesscoin": 26
    },
    {
      "name": "Siciliano Pablo",
      "chesscoin": 8
    },
    {
      "name": "Smikus Federico",
      "chesscoin": 17
    },
    {
      "name": "Solano Pablo",
      "chesscoin": 21
    },
    {
      "name": "Sosa Pablo",
      "chesscoin": 0
    },
    {
      "name": "Sotelo Ivan",
      "chesscoin": 22
    },
    {
      "name": "Spagnoli Eugenio",
      "chesscoin": 114
    },
    {
      "name": "Spizzirri Damian",
      "chesscoin": 0
    },
    {
      "name": "Torres Martin",
      "chesscoin": 1
    },
    {
      "name": "Troche Emmanuel",
      "chesscoin": 0
    },
    {
      "name": "Ucha Luis",
      "chesscoin": 34
    },
    {
      "name": "Uncal Jose",
      "chesscoin": 86
    },
    {
      "name": "Unger Alberto",
      "chesscoin": 10
    },
    {
      "name": "Varela Ricardo",
      "chesscoin": 30
    },
    {
      "name": "Vega Fernando",
      "chesscoin": 49
    },
    {
      "name": "Vicaria Alejandro",
      "chesscoin": 10
    },
    {
      "name": "Villalba Anibal",
      "chesscoin": 7
    },
    {
      "name": "Viola Francisco",
      "chesscoin": -35
    },
    {
      "name": "Wald Gabriel",
      "chesscoin": -1
    },
    {
      "name": "Wester Mariano",
      "chesscoin": 0
    },
    {
      "name": "Xalambri Claudio",
      "chesscoin": 11
    },
    {
      "name": "Zapata Elias",
      "chesscoin": 0
    },
    {
    "name": "Acuña Betiana",
    "chesscoin": 22
    },
    {
    "name": "Albornoz Molinari Aleli",
    "chesscoin": 35
    },
    {
    "name": "Clamades Laura",
    "chesscoin": 0
    },
    {
    "name": "De lazzari Felicitas",
    "chesscoin": 35
    },
    {
    "name": "De lazzari Margarita",
    "chesscoin": 13
    },
    {
    "name": "Diaz Niño Sofia",
    "chesscoin": 21
    },
    {
    "name": "Elisseche Celeste",
    "chesscoin": 13
    },
    {
    "name": "Esquivel Belen",
    "chesscoin": 93
    },
    {
    "name": "Fernandez Valentina",
    "chesscoin": 84
    },
    {
    "name": "Garcia Lucia",
    "chesscoin": 151
    },
    {
    "name": "Genes Ingrid",
    "chesscoin": 0
    },
    {
    "name": "Genovese Cristina",
    "chesscoin": 0
    },
    {
    "name": "Gomez Reyes Solana",
    "chesscoin": 51
    },
    {
    "name": "Gonzalez Ariadna",
    "chesscoin": 0
    },
    {
    "name": "Guzman Vanesa",
    "chesscoin": 74
    },
    {
    "name": "Jofre Ailin",
    "chesscoin": 182
    },
    {
    "name": "Kutianski Sofia",
    "chesscoin": 154
    },
    {
    "name": "Lelic Giulia",
    "chesscoin": 0
    },
    {
    "name": "Lozano Maria Teresa",
    "chesscoin": -35
    },
    {
    "name": "Olmos Florencia",
    "chesscoin": 70
    },
    {
    "name": "Ondina Gumeiro Angela",
    "chesscoin": 44
    },
    {
    "name": "Polo Loana",
    "chesscoin": 0
    },
    {
    "name": "Rivero Fabiana",
    "chesscoin": 12
    },
    {
    "name": "Sagodian Lucrecia",
    "chesscoin": 1
    },
    {
    "name": "Sanchez Abril",
    "chesscoin": 12.5
    },
    {
    "name": "Sanchez Belen",
    "chesscoin": 22
    },
    {
    "name": "Savia Milagros",
    "chesscoin": 0
    },
    {
    "name": "Semprevivo Florencia",
    "chesscoin": 148
    },
    {
    "name": "Spizzirri Stella",
    "chesscoin": 28
    }
  ]